combgc.py
combgc-0.6.9.dist-info/licenses/LICENSE
functions/__init__.py
functions/antismash_workflow.py
functions/deepbgc_workflow.py
functions/filter.py
functions/gecco_workflow.py
combgc-0.6.9.dist-info/METADATA
combgc-0.6.9.dist-info/WHEEL
combgc-0.6.9.dist-info/entry_points.txt
combgc-0.6.9.dist-info/top_level.txt
combgc-0.6.9.dist-info/RECORD
