Metadata-Version: 2.4
Name: combgc
Version: 0.6.9
Summary: A tool that aggregates, filters and combines the results of BGC prediction tools: antiSMASH, deepBGC, and GECCO.
Author-email: Tom Richtermeier <tom.richtermeier@gmx.de>
Maintainer-email: Tom Richtermeier <tom.richtermeier@gmx.de>, Anan Ibrahim <ananhamido@hotmail.com>
License: MIT License
Project-URL: Homepage, https://github.com/tomrichtermeier/comBGC-Filter/tree/main
Project-URL: Issues, https://github.com/tomrichtermeier/comBGC-Filter/issues
Project-URL: Source, https://github.com/tomrichtermeier/comBGC-Filter
Keywords: biosynthetic-gene-clusters,bioinformatics,genes,bgc
Classifier: Environment :: Console
Classifier: Development Status :: 4 - Beta
Classifier: Programming Language :: Python :: 3.12
Classifier: License :: OSI Approved :: MIT License
Classifier: Operating System :: OS Independent
Requires-Python: >=3.8
License-File: LICENSE
Requires-Dist: biopython>=1.79
Requires-Dist: pandas>=1.0
Dynamic: license-file
